[{"id":1,"full_name":"Abbye","email":"aarsey0@cbc.ca","gender":"Female"},
{"id":2,"full_name":"Scott","email":"sdallyn1@zdnet.com","gender":"Male"},
{"id":3,"full_name":"Rhonda","email":"raccomb2@pcworld.com","gender":"Female"},
{"id":4,"full_name":"Eldin","email":"egorgl3@engadget.com","gender":"Male"},
{"id":5,"full_name":"Natasha","email":"ncoulbeck4@tmall.com","gender":"Female"},
{"id":6,"full_name":"Emeline","email":"egiovannelli5@clickbank.net","gender":"Bigender"},
{"id":7,"full_name":"Lurlene","email":"ldenisovich6@arizona.edu","gender":"Female"},
{"id":8,"full_name":"Ralf","email":"rtrott7@ihg.com","gender":"Male"},
{"id":9,"full_name":"Muriel","email":"mmccandless8@macromedia.com","gender":"Female"},
{"id":10,"full_name":"Crissie","email":"ckemwal9@cisco.com","gender":"Female"},
{"id":11,"full_name":"Myrta","email":"mvidoa@g.co","gender":"Female"},
{"id":12,"full_name":"Pierrette","email":"probilartb@issuu.com","gender":"Female"},
{"id":13,"full_name":"Gennie","email":"golunneyc@si.edu","gender":"Female"},
{"id":14,"full_name":"Clerkclaude","email":"csictornesd@simplemachines.org","gender":"Male"},
{"id":15,"full_name":"Kesley","email":"kpundye@lulu.com","gender":"Female"},
{"id":16,"full_name":"Larine","email":"llesorf@phoca.cz","gender":"Female"},
{"id":17,"full_name":"Rafe","email":"rduckelsg@lycos.com","gender":"Male"},
{"id":18,"full_name":"Bat","email":"bedelmanh@oakley.com","gender":"Male"},
{"id":19,"full_name":"Kiley","email":"kpakemani@time.com","gender":"Female"},
{"id":20,"full_name":"Drusilla","email":"dsaggj@spotify.com","gender":"Female"},
{"id":21,"full_name":"Shirley","email":"scolquytek@economist.com","gender":"Female"},
{"id":22,"full_name":"Susanna","email":"sfarlanel@hostgator.com","gender":"Female"},
{"id":23,"full_name":"Katherine","email":"kgreensladem@google.cn","gender":"Female"},
{"id":24,"full_name":"Cordy","email":"cshermen@indiegogo.com","gender":"Male"},
{"id":25,"full_name":"Thorvald","email":"thathorno@nasa.gov","gender":"Male"}]